libcomcat/__init__.py
libcomcat/_version.py
libcomcat/classes.py
libcomcat/dataframes.py
libcomcat/exceptions.py
libcomcat/logging.py
libcomcat/search.py
libcomcat/test_utils.py
libcomcat/utils.py
libcomcat/visualization.py
libcomcat/bin/__init__.py
libcomcat/bin/findid.py
libcomcat/bin/getcsv.py
libcomcat/bin/geteventhist.py
libcomcat/bin/getmags.py
libcomcat/bin/getpager.py
libcomcat/bin/getphases.py
libcomcat/bin/getproduct.py
libcomcat/data/economy.xml
libcomcat/data/fatality.xml
libcomcat/data/gf-landslide-green.png
libcomcat/data/gf-landslide-orange.png
libcomcat/data/gf-landslide-red.png
libcomcat/data/gf-landslide-yellow.png
libcomcat/data/gf-liquefaction-green.png
libcomcat/data/gf-liquefaction-orange.png
libcomcat/data/gf-liquefaction-red.png
libcomcat/data/gf-liquefaction-yellow.png
libcomcat/data/ne_50m_admin_0_countries.cpg
libcomcat/data/ne_50m_admin_0_countries.dbf
libcomcat/data/ne_50m_admin_0_countries.prj
libcomcat/data/ne_50m_admin_0_countries.shp
libcomcat/data/ne_50m_admin_0_countries.shx
usgs_libcomcat-2.1.12.dist-info/LICENSE.md
usgs_libcomcat-2.1.12.dist-info/METADATA
usgs_libcomcat-2.1.12.dist-info/WHEEL
usgs_libcomcat-2.1.12.dist-info/entry_points.txt
usgs_libcomcat-2.1.12.dist-info/top_level.txt
usgs_libcomcat-2.1.12.dist-info/RECORD
