Metadata-Version: 2.1
Name: usgs-libcomcat
Version: 2.1.12
Summary: Python wrapper around ComCat web API
Author-email: Mike Hearne <mhearne@usgs.gov>, Heather Hunsinger <hhunsinger@usgs.gov>
Keywords: comcat,earthquake
Requires-Python: >=3.7
License-File: LICENSE.md
Requires-Dist: esi_utils_colors>=1.0.3
Requires-Dist: esi_utils_geo
Requires-Dist: esi-utils-rupture
Requires-Dist: esi_utils_time
Requires-Dist: esi_utils_io
Requires-Dist: fiona>=1.8.20
Requires-Dist: geopy>=2.1.0
Requires-Dist: h5py
Requires-Dist: numba
Requires-Dist: numpy>=1.21
Requires-Dist: obspy>=1.2.1
Requires-Dist: pandas>=1.3.3
Requires-Dist: openpyxl>=3.0.6
Requires-Dist: numpy>=1.21.0
Requires-Dist: pandas>=1.4.1
Requires-Dist: requests
Requires-Dist: urllib3<1.27,>=1.25.4
Requires-Dist: xlsxwriter>=3.0.1
Provides-Extra: dev
Requires-Dist: build>=0.7.0; extra == "dev"
Requires-Dist: black>=21; extra == "dev"
Requires-Dist: flake8>=3.9; extra == "dev"
Requires-Dist: ipython>=7.26; extra == "dev"
Requires-Dist: notebook>=6.4.0; extra == "dev"
Requires-Dist: geopy>=2.2.0; extra == "dev"
Requires-Dist: twine>=3.5.0; extra == "dev"
Provides-Extra: test
Requires-Dist: pytest>=6.2; extra == "test"
Requires-Dist: pytest-cov>=2.12.0; extra == "test"
Requires-Dist: vcrpy>=4.1; extra == "test"
Provides-Extra: build
Requires-Dist: build; extra == "build"
Requires-Dist: twine==6.0.1; extra == "build"
Requires-Dist: check-wheel-contents; extra == "build"
